personal_trainer/__init__.py
personal_trainer/label_mapper.py
personal_trainer/mlp_classifier.py
personal_trainer/text_classifier.py
model_personal_trainer-0.1.0.dist-info/LICENSE
model_personal_trainer-0.1.0.dist-info/METADATA
model_personal_trainer-0.1.0.dist-info/WHEEL
model_personal_trainer-0.1.0.dist-info/RECORD
