Metadata-Version: 2.1
Name: model-personal-trainer
Version: 0.1.0
Summary: An easy-to-use library for training personalized AI models
License: MIT
Author: Brian Smith
Author-email: ohohvi@gmail.com
Requires-Python: >=3.10,<3.13
Classifier: License :: OSI Approved :: MIT License
Classifier: Programming Language :: Python :: 3
Classifier: Programming Language :: Python :: 3.10
Classifier: Programming Language :: Python :: 3.11
Requires-Dist: datasets (>=2.14.5,<3.0.0)
Requires-Dist: numpy (>=1.26.0,<2.0.0)
Requires-Dist: transformers[torch] (>=4.34.1,<5.0.0)
